jarvis/.DS_Store
jarvis/__init__.py
jarvis/__pycache__/__init__.cpython-39.pyc
jarvis/cli/.DS_Store
jarvis/cli/__init__.py
jarvis/cli/entrypoint.py
jarvis/cli/__pycache__/__init__.cpython-39.pyc
jarvis/cli/__pycache__/entrypoint.cpython-39.pyc
jarvis/cli/src/.DS_Store
jarvis/cli/src/__init__.py
jarvis/cli/src/jarvis.py
jarvis/cli/src/__pycache__/__init__.cpython-39.pyc
jarvis/cli/src/__pycache__/jarvis.cpython-39.pyc
jarvis/cli/src/res/success.mp3
jarvis_grabfood-1.0.8.dist-info/METADATA
jarvis_grabfood-1.0.8.dist-info/WHEEL
jarvis_grabfood-1.0.8.dist-info/entry_points.txt
jarvis_grabfood-1.0.8.dist-info/top_level.txt
jarvis_grabfood-1.0.8.dist-info/zip-safe
jarvis_grabfood-1.0.8.dist-info/RECORD
