Metadata-Version: 2.1
Name: jarvis-grabfood
Version: 1.0.8
Summary: grabfood
Home-page: UNKNOWN
Author: mafei
License: GNU GPLv3
Platform: any
Requires-Python: >=3
Requires-Dist: click
Requires-Dist: jmdevice
Requires-Dist: uiautomator2
Requires-Dist: playsound
Requires-Dist: PyObjC
